ketcher/__init__.py
ketcher/build/asset-manifest.json
ketcher/build/favicon.ico
ketcher/build/index.html
ketcher/build/manifest.json
ketcher/build/robots.txt
ketcher/build/js/ketcherFunctions.js
ketcher/build/js/streamlitFunctions.js
ketcher/build/static/css/main.6b7c7589.css
ketcher/build/static/js/420.7ae3182e.chunk.js
ketcher/build/static/js/main.e849a0fd.js
ketcher/build/static/js/main.e849a0fd.js.LICENSE.txt
ketcher/build/templates/fg.sdf
ketcher/build/templates/library.sdf
ketcher/build/templates/library.svg
nafld_kbd_nav/__init__.py
nafld_kbd_nav/frontend/dist/favicon.ico
nafld_kbd_nav/frontend/dist/index.html
nafld_kbd_nav/frontend/dist/assets/flUhRq6tzZclQEJ-Vdg-IuiaDsNa.812f3b69.woff
nafld_kbd_nav/frontend/dist/assets/flUhRq6tzZclQEJ-Vdg-IuiaDsNcIhQ8tQ.a0978f67.woff2
nafld_kbd_nav/frontend/dist/assets/index.26f4d98a.js
nafld_kbd_nav/frontend/dist/assets/index.3ace2fc5.css
nafld_kbd_nav/frontend/dist/assets/nafld_kbd_logo.c88be480.svg
nafld_kbd_search/__init__.py
nafld_kbd_search/frontend/dist/favicon.ico
nafld_kbd_search/frontend/dist/index.html
nafld_kbd_search/frontend/dist/css/app.fc778ff0.css
nafld_kbd_search/frontend/dist/css/chunk-vendors.ce7ff385.css
nafld_kbd_search/frontend/dist/fonts/dxicons.4f5b3dc6.woff2
nafld_kbd_search/frontend/dist/fonts/dxicons.993aa209.ttf
nafld_kbd_search/frontend/dist/fonts/dxicons.a7f0b675.woff
nafld_kbd_search/frontend/dist/js/app.c2b28b37.js
nafld_kbd_search/frontend/dist/js/app.c2b28b37.js.map
nafld_kbd_search/frontend/dist/js/chunk-vendors.bc92c974.js
nafld_kbd_search/frontend/dist/js/chunk-vendors.bc92c974.js.map
nafld_kbd_stats/__init__.py
nafld_kbd_stats/frontend/dist/favicon.ico
nafld_kbd_stats/frontend/dist/index.html
nafld_kbd_stats/frontend/dist/assets/index.29df042d.css
nafld_kbd_stats/frontend/dist/assets/index.2e80755f.js
nafld_kbd_stats/frontend/dist/assets/materialdesignicons-webfont.8bded8f4.woff
nafld_kbd_stats/frontend/dist/assets/materialdesignicons-webfont.9bdfaf27.eot
nafld_kbd_components-0.0.1.dist-info/METADATA
nafld_kbd_components-0.0.1.dist-info/WHEEL
nafld_kbd_components-0.0.1.dist-info/top_level.txt
nafld_kbd_components-0.0.1.dist-info/RECORD
