Metadata-Version: 2.1
Name: nafld_kbd_components
Version: 0.0.1
Summary: Custom Streamlit Components for NAFLD KBD
Author: zhifeng-essen
Author-email: zhifeng_essen@icloud.com
License: UNKNOWN
Platform: UNKNOWN
